README.md
setup.cfg
setup.py
namepy/__init__.py
namepy/__main__.py
namepy/lexicon.py
namepy/namepy.py
namepy/nouns.py
namepy/version.py
namepy.egg-info/PKG-INFO
namepy.egg-info/SOURCES.txt
namepy.egg-info/dependency_links.txt
namepy.egg-info/entry_points.txt
namepy.egg-info/top_level.txt