Metadata-Version: 1.1
Name: namepy
Version: 1.1.0
Summary: Command-line tool to generate names for the uncreative
Home-page: https://github.com/mdmedley/namepy
Author: Marcus Medley
Author-email: mdmeds@gmail.com
License: MIT
Keywords: names,naming,name,generator
Platform: UNKNOWN
Classifier: Development Status :: 5 - Production/Stable
Classifier: Natural Language :: English
Classifier: License :: OSI Approved :: MIT License
Classifier: Programming Language :: Python :: 2.7
Classifier: Programming Language :: Python :: 3.4
Classifier: Programming Language :: Python :: 3.5
Classifier: Programming Language :: Python :: 3.6
Classifier: Programming Language :: Python :: 3.7
Classifier: Topic :: Utilities
